chainswarm_analyzers_baseline/__init__.py
chainswarm_analyzers_baseline/adapters/__init__.py
chainswarm_analyzers_baseline/adapters/clickhouse.py
chainswarm_analyzers_baseline/adapters/parquet.py
chainswarm_analyzers_baseline/aggregates/__init__.py
chainswarm_analyzers_baseline/aggregates/transfer_aggregates.py
chainswarm_analyzers_baseline/config/__init__.py
chainswarm_analyzers_baseline/config/settings_loader.py
chainswarm_analyzers_baseline/config/defaults/structural_pattern_settings.json
chainswarm_analyzers_baseline/features/__init__.py
chainswarm_analyzers_baseline/features/address_feature_analyzer.py
chainswarm_analyzers_baseline/graph/__init__.py
chainswarm_analyzers_baseline/graph/builder.py
chainswarm_analyzers_baseline/patterns/__init__.py
chainswarm_analyzers_baseline/patterns/base_detector.py
chainswarm_analyzers_baseline/patterns/structural_pattern_analyzer.py
chainswarm_analyzers_baseline/patterns/detectors/__init__.py
chainswarm_analyzers_baseline/patterns/detectors/burst_detector.py
chainswarm_analyzers_baseline/patterns/detectors/cycle_detector.py
chainswarm_analyzers_baseline/patterns/detectors/layering_detector.py
chainswarm_analyzers_baseline/patterns/detectors/motif_detector.py
chainswarm_analyzers_baseline/patterns/detectors/network_detector.py
chainswarm_analyzers_baseline/patterns/detectors/proximity_detector.py
chainswarm_analyzers_baseline/patterns/detectors/threshold_detector.py
chainswarm_analyzers_baseline/pipeline/__init__.py
chainswarm_analyzers_baseline/pipeline/baseline.py
chainswarm_analyzers_baseline/protocols/__init__.py
chainswarm_analyzers_baseline/protocols/analyzer.py
chainswarm_analyzers_baseline/protocols/io.py
chainswarm_analyzers_baseline/protocols/models.py
chainswarm_analyzers_baseline/scripts/__init__.py
chainswarm_analyzers_baseline/scripts/run_features.py
chainswarm_analyzers_baseline/scripts/run_patterns.py
chainswarm_analyzers_baseline/scripts/run_pipeline.py
chainswarm_analyzers_baseline-0.2.3.dist-info/licenses/LICENSE
chainswarm_analyzers_baseline-0.2.3.dist-info/METADATA
chainswarm_analyzers_baseline-0.2.3.dist-info/WHEEL
chainswarm_analyzers_baseline-0.2.3.dist-info/entry_points.txt
chainswarm_analyzers_baseline-0.2.3.dist-info/top_level.txt
chainswarm_analyzers_baseline-0.2.3.dist-info/RECORD
