Metadata-Version: 2.4
Name: chainswarm-analyzers-baseline
Version: 0.2.3
Summary: Baseline analytics algorithms for blockchain pattern detection and feature engineering
Author: ChainSwarm Team
License: Apache-2.0
Project-URL: Homepage, https://github.com/chainswarm/analyzers-baseline
Project-URL: Repository, https://github.com/chainswarm/analyzers-baseline
Project-URL: Documentation, https://github.com/chainswarm/analyzers-baseline#readme
Project-URL: Changelog, https://github.com/chainswarm/analyzers-baseline/blob/main/CHANGELOG.md
Keywords: blockchain,analytics,pattern-detection,aml,fraud-detection,chainswarm
Classifier: Development Status :: 4 - Beta
Classifier: Intended Audience :: Developers
Classifier: Programming Language :: Python :: 3
Classifier: Programming Language :: Python :: 3.13
Classifier: License :: OSI Approved :: Apache Software License
Classifier: Operating System :: OS Independent
Classifier: Topic :: Scientific/Engineering :: Information Analysis
Requires-Python: >=3.13
License-File: LICENSE
Requires-Dist: chainswarm-core>=0.1.13
Requires-Dist: networkx>=3.0
Requires-Dist: numpy>=1.24
Requires-Dist: cdlib>=0.4.0
Requires-Dist: python-igraph>=0.11.0
Requires-Dist: leidenalg>=0.10.0
Requires-Dist: scipy>=1.11.0
Requires-Dist: pandas>=2.0
Requires-Dist: pyarrow>=14.0
Requires-Dist: click>=8.0
Dynamic: license-file
